{
    "kind": "user",
    "id": "2025-03_gdm_bedazzle",
    "label": "GDM Bedazzle",
    "defaultConfig": {
        "enabled": false,
        "unifiedEditing": false
    },
    "treatments": [
        {
            "id": 1,
            "label": "Enabled - T1 - Unified editing",
            "config": {
                "enabled": true,
                "unifiedEditing": true
            }
        },
        {
            "id": 2,
            "label": "Enabled - T2 - Retain Change Icon",
            "config": {
                "enabled": true,
                "unifiedEditing": false
            }
        }
    ]
}